pgpt_python/__init__.py
pgpt_python/client.py
pgpt_python/core/__init__.py
pgpt_python/core/api_error.py
pgpt_python/core/client_wrapper.py
pgpt_python/core/datetime_utils.py
pgpt_python/core/jsonable_encoder.py
pgpt_python/core/remove_none_from_dict.py
pgpt_python/errors/__init__.py
pgpt_python/errors/unprocessable_entity_error.py
pgpt_python/resources/__init__.py
pgpt_python/resources/context_chunks/__init__.py
pgpt_python/resources/context_chunks/client.py
pgpt_python/resources/contextual_completions/__init__.py
pgpt_python/resources/contextual_completions/client.py
pgpt_python/resources/embeddings/__init__.py
pgpt_python/resources/embeddings/client.py
pgpt_python/resources/health/__init__.py
pgpt_python/resources/health/client.py
pgpt_python/resources/ingestion/__init__.py
pgpt_python/resources/ingestion/client.py
pgpt_python/types/__init__.py
pgpt_python/types/chat_body.py
pgpt_python/types/chunk.py
pgpt_python/types/chunks_response.py
pgpt_python/types/completions_body.py
pgpt_python/types/context_filter.py
pgpt_python/types/embedding.py
pgpt_python/types/embeddings_body_input.py
pgpt_python/types/embeddings_response.py
pgpt_python/types/health_response.py
pgpt_python/types/http_validation_error.py
pgpt_python/types/ingest_response.py
pgpt_python/types/ingested_doc.py
pgpt_python/types/open_ai_choice.py
pgpt_python/types/open_ai_completion.py
pgpt_python/types/open_ai_completion_object.py
pgpt_python/types/open_ai_delta.py
pgpt_python/types/open_ai_message.py
pgpt_python/types/open_ai_message_role.py
pgpt_python/types/validation_error.py
pgpt_python/types/validation_error_loc_item.py
pgpt_python-0.1.2.dist-info/LICENSE
pgpt_python-0.1.2.dist-info/METADATA
pgpt_python-0.1.2.dist-info/WHEEL
pgpt_python-0.1.2.dist-info/RECORD
