Metadata-Version: 2.1
Name: pgpt_python
Version: 0.1.2
Summary: PrivateGPT Python SDK
Author: imartinez
Author-email: ivanmartit@gmail.com
Requires-Python: >=3.11,<4.0
Classifier: Programming Language :: Python :: 3
Classifier: Programming Language :: Python :: 3.11
Classifier: Programming Language :: Python :: 3.12
Requires-Dist: httpx (>=0.26.0,<0.27.0)
Requires-Dist: pydantic (>=2.5.3,<3.0.0)
